{
    "translations": {
        "UNCLEFROST": [
            "Uncle Frost (Event Musim Dingin)",
            "🥶",
            "EVENT_BOSS"
        ],
        "ANNIVERSARY_TITAN": [
            "Titan Anniversary (Event)",
            "⚔️",
            "EVENT_BOSS"
        ],
        "RANDOM_EVENT_WINTER_STANDARD_BOSS": [
            "Bos Standar (Event Musim Dingin)",
            "☃️",
            "EVENT_BOSS"
        ],
        "RANDOM_EVENT_WINTER_VETERAN_BOSS": [
            "Bos Veteran (Event Musim Dingin)",
            "☃️❄️",
            "EVENT_BOSS"
        ],
        "RANDOM_RD_ANNIVERSARY_SOLO_BOSS": [
            "Bos Anniversary Solo (Event)",
            "🎉",
            "EVENT_BOSS"
        ],
        "RANDOM_RD_ANNIVERSARY_VETERAN_BOSS": [
            "Bos Anniversary Veteran (Event)",
            "🎉🏆",
            "EVENT_BOSS"
        ],
        "RANDOM_HERETIC_SOLO_MINIBOSS": [
            "Minibos Heretic",
            "💀",
            "DUNGEON_BOSS"
        ],
        "RANDOM_HERETIC_VETERAN_MINIBOSS": [
            "Minibos Heretic Veteran",
            "💀",
            "DUNGEON_BOSS"
        ],
        "RANDOM_HERETIC_SOLO_BOSS_HIGHLIGHT": [
            "Bos Heretic (Highlight)",
            "👻",
            "DUNGEON_BOSS"
        ],
        "RANDOM_HERETIC_VETERAN_BOSS_HIGHLIGHT": [
            "Bos Heretic Veteran (Highlight)",
            "👻",
            "DUNGEON_BOSS"
        ],
        "RANDOM_HERETIC_SOLO_ENDBOSS_UNCOMMON": [
            "Bos Akhir Heretic (Biru)",
            "👹",
            "DUNGEON_BOSS"
        ],
        "RANDOM_HERETIC_VETERAN_ENDBOSS_UNCOMMON": [
            "Bos Akhir Heretic Veteran (Biru)",
            "👹",
            "DUNGEON_BOSS"
        ],
        "RANDOM_KEEPER_SOLO_MINIBOSS": [
            "Minibos Keeper",
            "🌿💀",
            "DUNGEON_BOSS"
        ],
        "RANDOM_KEEPER_VETERAN_MINIBOSS": [
            "Minibos Keeper Veteran",
            "🌿💀",
            "DUNGEON_BOSS"
        ],
        "RANDOM_KEEPER_SOLO_BOSS_HIGHLIGHT": [
            "Bos Keeper (Highlight)",
            "🌿👻",
            "DUNGEON_BOSS"
        ],
        "RANDOM_KEEPER_VETERAN_BOSS_HIGHLIGHT": [
            "Bos Keeper Veteran (Highlight)",
            "🌿👻",
            "DUNGEON_BOSS"
        ],
        "RANDOM_KEEPER_SOLO_ENDBOSS_RARE_CHIEFTAIN": [
            "Chieftain Keeper (Ungu)",
            "🌿👹",
            "DUNGEON_BOSS"
        ],
        "RANDOM_KEEPER_VETERAN_ENDBOSS_RARE_CHIEFTAIN": [
            "Chieftain Keeper Veteran (Ungu)",
            "🌿👹",
            "DUNGEON_BOSS"
        ],
        "RANDOM_MORGANA_SOLO_MINIBOSS": [
            "Minibos Morgana",
            "⚔️💀",
            "DUNGEON_BOSS"
        ],
        "RANDOM_MORGANA_VETERAN_MINIBOSS": [
            "Minibos Morgana Veteran",
            "⚔️💀",
            "DUNGEON_BOSS"
        ],
        "RANDOM_MORGANA_SOLO_BOSS_HIGHLIGHT": [
            "Bos Morgana (Highlight)",
            "⚔️👻",
            "DUNGEON_BOSS"
        ],
        "RANDOM_MORGANA_VETERAN_BOSS_HIGHLIGHT": [
            "Bos Morgana Veteran (Highlight)",
            "⚔️👻",
            "DUNGEON_BOSS"
        ],
        "RANDOM_MORGANA_SOLO_ENDBOSS_UNCOMMON": [
            "Bos Akhir Morgana (Biru)",
            "⚔️👹",
            "DUNGEON_BOSS"
        ],
        "RANDOM_MORGANA_VETERAN_ENDBOSS_UNCOMMON": [
            "Bos Akhir Morgana Veteran (Biru)",
            "⚔️👹",
            "DUNGEON_BOSS"
        ],
        "RANDOM_UNDEAD_SOLO_ENDBOSS_UNCOMMON_GENERAL": [
            "Bos Akhir Undead (Umum)",
            "💀👹",
            "DUNGEON_BOSS"
        ],
        "SHRINE_FAME_BUFF": [
            "Altar Peningkatan Fame",
            "📈",
            "SHRINE"
        ],
        "SHRINE_COMBAT_BUFF": [
            "Altar Kekuatan Tempur",
            "💥",
            "SHRINE"
        ],
        "SHRINE_DEFENSE_BUFF": [
            "Altar Pertahanan",
            "🛡️",
            "SHRINE"
        ],
        "SHRINE_ENERGY_REGEN_BUFF": [
            "Altar Regenerasi Energi",
            "⚡",
            "SHRINE"
        ],
        "SHRINE_HEALTH_REGEN_BUFF": [
            "Altar Regenerasi HP",
            "❤️",
            "SHRINE"
        ],
        "SHRINE_COOLDOWN_REDUCTION_BUFF": [
            "Altar Pengurangan Cooldown",
            "⏳",
            "SHRINE"
        ],
        "SHRINE_MOB_SPEED_BUFF": [
            "Altar Kecepatan Gerak",
            "🏃",
            "SHRINE"
        ],
        "LOOTCHEST_STANDARD": [
            "Peti Biasa (Hijau)",
            "🟩"
        ],
        "LOOTCHEST_UNCOMMON": [
            "Peti Tidak Biasa (Biru)",
            "🟦"
        ],
        "LOOTCHEST_RARE": [
            "Peti Langka (Ungu)",
            "🟪"
        ],
        "LOOTCHEST_LEGENDARY": [
            "Peti Legendaris (Emas)",
            "🟨"
        ],
        "LOOTCHEST_KEEPER_SOLO_UNCOMMON": [
            "Peti Keeper Solo (Biru)",
            "🟦"
        ],
        "LOOTCHEST_ANNIVERSARY_SOLO_LOOTCHEST_BOSS": [
            "Peti Boss Anniversary Solo",
            "🎂"
        ]
    },
    "timestamps": {}
}